README.rst
setup.cfg
setup.py
django_oss2_storage.egg-info/PKG-INFO
django_oss2_storage.egg-info/SOURCES.txt
django_oss2_storage.egg-info/dependency_links.txt
django_oss2_storage.egg-info/not-zip-safe
django_oss2_storage.egg-info/requires.txt
django_oss2_storage.egg-info/top_level.txt
oss2_storage/__init__.py
oss2_storage/backends.py