Metadata-Version: 1.1
Name: django-oss2-storage
Version: 1.0.1
Summary: Support for aliyun oss2 storage backends in Django
Home-page: https://github.com/keviswang/django-oss2-storage
Author: Kevis Wang
Author-email: keviswang@outlook.com
License: BSD
Platform: UNKNOWN
Classifier: Development Status :: 5 - Production/Stable
Classifier: Environment :: Web Environment
Classifier: Framework :: Django
Classifier: Framework :: Django :: 1.10
Classifier: Framework :: Django :: 1.11
Classifier: Intended Audience :: Developers
Classifier: License :: OSI Approved :: BSD License
Classifier: Operating System :: OS Independent
Classifier: Programming Language :: Python
Classifier: Programming Language :: Python :: 3.5
Classifier: Programming Language :: Python :: 3.6
